pythonbrewer/__init__.py
pythonbrewer/brew.py
pythonbrewer/cmdline.py
pythonbrewer/deplist.py
pythonbrewer/errors.py
pythonbrewer/pypi.py
python_brewer-0.3.0.dist-info/LICENSE.md
python_brewer-0.3.0.dist-info/METADATA
python_brewer-0.3.0.dist-info/WHEEL
python_brewer-0.3.0.dist-info/entry_points.txt
python_brewer-0.3.0.dist-info/top_level.txt
python_brewer-0.3.0.dist-info/RECORD
