Metadata-Version: 2.1
Name: python-brewer
Version: 0.3.0
Summary: A Homebrew formula template generator for Python packages
Home-page: https://github.com/thanethomson/python-brewer
Author: Thane Thomson
Author-email: connect@thanethomson.com
License: MIT
Platform: UNKNOWN
Classifier: Development Status :: 4 - Beta
Classifier: Environment :: Console
Classifier: Intended Audience :: Developers
Classifier: License :: OSI Approved :: MIT License
Classifier: Natural Language :: English
Classifier: Operating System :: POSIX
Classifier: Operating System :: MacOS
Classifier: Programming Language :: Python :: 2.7
Classifier: Programming Language :: Python :: 3.5
Classifier: Programming Language :: Python :: 3.6
Classifier: Programming Language :: Python :: 3.7
Classifier: Topic :: Utilities
Requires-Dist: future (>=0.16.0)
Requires-Dist: html5lib (>=1.0b8)
Requires-Dist: pip (>=9.0.1)
Requires-Dist: pipdeptree (>=0.9.0)
Requires-Dist: requests (>=2.12.5)
Requires-Dist: six (>=1.10.0)
